{
  "guid": "abde36d9-4550-4350-8c68-12ec4d5a3f8f",
  "name": "abde36d9-4550-4350-8c68-12ec4d5a3f8f",
  "readOnly": false,
  "title": {
      "en": "Questionnaire Title EN",
      "fr": "Questionnaire Title EN"
  },
  "groups": [
      {
          "domId": "",
          "domSuffix": "",
          "guid": "42f493b8-f24f-40a5-8878-2088349be0f8",
          "name": "42f493b8-f24f-40a5-8878-2088349be0f8",
          "sortOrder": 1,
          "title": {
              "en": "1.0 COMPANY DETAILS",
              "fr": "1.0 DÉTAILS DE LA COMPAGNIE"
          },
          "isRepeatable": false,
          "isVisible": true,
          "questions": [
              {
                  "guid": "2a52bb18-ff63-42e6-be03-84afe116deb7",
                  "name": "2a52bb18-ff63-42e6-be03-84afe116deb7",
                  "sortOrder": 1,
                  "text": {
                      "en": "1.01 Type of Inspection",
                      "fr": "1.01 Type d'inspection"
                  },
                  "type": "select",
                  "isRepeatable": false,
                  "isRepeated": false,
                  "isSamplingAllowed": false,
                  "isVisible": true,
                  "validationState": true,
                  "responseOptions": [
                      {
                          "guid": "300f1ce2-7eb2-4927-92b1-ea7acf92ce69",
                          "name": "300f1ce2-7eb2-4927-92b1-ea7acf92ce69",
                          "sortOrder": 1,
                          "text": {
                              "en": "Initial",
                              "fr": "Initiale"
                          },
                          "value": "1",
                          "internalCommentRequirement": "optional",
                          "externalCommentRequirement": "optional",
                          "pictureRequirement": "optional",
                          "fileRequirement": "optional",
                          "provisions": []
                      },
                      {
                          "guid": "4f7f4191-22ff-4083-b55d-f8e83360d1ed",
                          "name": "4f7f4191-22ff-4083-b55d-f8e83360d1ed",
                          "sortOrder": 2,
                          "text": {
                              "en": "Verification",
                              "fr": "Vérification"
                          },
                          "value": "2",
                          "internalCommentRequirement": "optional",
                          "externalCommentRequirement": "optional",
                          "pictureRequirement": "optional",
                          "fileRequirement": "optional",
                          "provisions": []
                      }
                  ],
                  "validationRules": [
                      {
                          "guid": "5fa9b65a-c959-4c0f-9f32-542672894416",
                          "enabled": true,
                          "errorMessage": {
                              "en": "Required",
                              "fr": "FR: Required"
                          },
                          "name": "require",
                          "type": "require",
                          "value": null
                      }
                  ],
                  "dependants": [
                      {
                          "guid": "91ad851b-18b9-421f-a5a8-e3ba1b5dc57a"
                      },
                      {
                          "guid": "379230fa-1830-4ef5-9f00-a9e68c60efc0"
                      },
                      {
                          "guid": "bc949298-dc79-49a3-ab67-bea5613bad34"
                      },
                      {
                          "guid": "730e2609-d56f-4a3d-9020-132fb394d2c6"
                      }
                  ],
                  "dependencyGroups": [],
                  "childQuestions": [
                      {
                          "guid": "bc949298-dc79-49a3-ab67-bea5613bad34",
                          "name": "bc949298-dc79-49a3-ab67-bea5613bad34",
                          "sortOrder": 1,
                          "text": {
                              "en": "1.01a If initial inspection, physical address matches address on application for registration?",
                              "fr": "1.01a S'il s'agit d'une inspection initiale, l'adresse physique correspond à la demande d'inscription?"
                          },
                          "type": "radio",
                          "isRepeatable": false,
                          "isRepeated": false,
                          "isSamplingAllowed": false,
                          "isVisible": false,
                          "validationState": true,
                          "responseOptions": [
                              {
                                  "guid": "2c360c1e-cb98-45b9-8f3b-f0f71be4524e",
                                  "name": "2c360c1e-cb98-45b9-8f3b-f0f71be4524e",
                                  "sortOrder": 1,
                                  "text": {
                                      "en": "Yes",
                                      "fr": "Oui"
                                  },
                                  "value": "true",
                                  "internalCommentRequirement": "optional",
                                  "externalCommentRequirement": "optional",
                                  "pictureRequirement": "optional",
                                  "fileRequirement": "optional",
                                  "provisions": []
                              },
                              {
                                  "guid": "c4a11c8b-1d06-48bc-91e2-2fbd3957308a",
                                  "name": "c4a11c8b-1d06-48bc-91e2-2fbd3957308a",
                                  "sortOrder": 2,
                                  "text": {
                                      "en": "No",
                                      "fr": "Non"
                                  },
                                  "value": "false",
                                  "internalCommentRequirement": "optional",
                                  "externalCommentRequirement": "required",
                                  "pictureRequirement": "optional",
                                  "fileRequirement": "optional",
                                  "provisions": []
                              },
                              {
                                  "guid": "e78dae69-95f7-40a5-bbe9-391cc3b05727",
                                  "name": "e78dae69-95f7-40a5-bbe9-391cc3b05727",
                                  "sortOrder": 3,
                                  "text": {
                                      "en": "Not inspected ",
                                      "fr": "Non inspecté "
                                  },
                                  "value": "3",
                                  "internalCommentRequirement": "optional",
                                  "externalCommentRequirement": "optional",
                                  "pictureRequirement": "optional",
                                  "fileRequirement": "optional",
                                  "provisions": []
                              }
                          ],
                          "validationRules": [
                              {
                                  "guid": "6284eb0e-e78b-4507-91da-4ae1fac10f95",
                                  "enabled": true,
                                  "errorMessage": {
                                      "en": "Required",
                                      "fr": "FR: Required"
                                  },
                                  "name": "require",
                                  "type": "require",
                                  "value": null
                              }
                          ],
                          "dependants": [],
                          "dependencyGroups": [
                              {
                                  "guid": "137f0ff8-d9cb-43a7-b27d-63a2657df3a9",
                                  "ruleType": "visibility",
                                  "childValidatorName": null,
                                  "questionDependencies": [
                                      {
                                          "guid": "547d66ad-6120-49ff-8d76-beabdb8692ed",
                                          "dependsOnQuestion": {
                                              "guid": "2a52bb18-ff63-42e6-be03-84afe116deb7"
                                          },
                                          "validationAction": "equal",
                                          "validationValue": "1"
                                      }
                                  ]
                              }
                          ],
                          "childQuestions": [],
                          "result": null
                      },
                      {
                          "guid": "730e2609-d56f-4a3d-9020-132fb394d2c6",
                          "name": "730e2609-d56f-4a3d-9020-132fb394d2c6",
                          "sortOrder": 2,
                          "text": {
                              "en": "1.01b If verification inspection, physical address matches address on Certificate of Registration?",
                              "fr": "1.01b S'il s'agit d'une inspection de vérification, l'adresse physique correspond au Certificat d'inscription?"
                          },
                          "type": "radio",
                          "isRepeatable": false,
                          "isRepeated": false,
                          "isSamplingAllowed": false,
                          "isVisible": false,
                          "validationState": true,
                          "responseOptions": [
                              {
                                  "guid": "23e51970-8ded-4359-a181-4a35a7065f73",
                                  "name": "23e51970-8ded-4359-a181-4a35a7065f73",
                                  "sortOrder": 1,
                                  "text": {
                                      "en": "Yes",
                                      "fr": "Oui"
                                  },
                                  "value": "true",
                                  "internalCommentRequirement": "optional",
                                  "externalCommentRequirement": "optional",
                                  "pictureRequirement": "optional",
                                  "fileRequirement": "optional",
                                  "provisions": []
                              },
                              {
                                  "guid": "6bfe1762-a80e-496d-9a9b-efae8b0ef857",
                                  "name": "6bfe1762-a80e-496d-9a9b-efae8b0ef857",
                                  "sortOrder": 2,
                                  "text": {
                                      "en": "No",
                                      "fr": "Non"
                                  },
                                  "value": "false",
                                  "internalCommentRequirement": "optional",
                                  "externalCommentRequirement": "required",
                                  "pictureRequirement": "optional",
                                  "fileRequirement": "optional",
                                  "provisions": []
                              },
                              {
                                  "guid": "b114cbd0-ae15-45a9-a86b-34ad2060bc78",
                                  "name": "b114cbd0-ae15-45a9-a86b-34ad2060bc78",
                                  "sortOrder": 3,
                                  "text": {
                                      "en": "Not inspected ",
                                      "fr": "Non inspecté "
                                  },
                                  "value": "3",
                                  "internalCommentRequirement": "optional",
                                  "externalCommentRequirement": "optional",
                                  "pictureRequirement": "optional",
                                  "fileRequirement": "optional",
                                  "provisions": []
                              }
                          ],
                          "validationRules": [
                              {
                                  "guid": "96da8d12-d8e3-4b0b-b884-b9fa20579adf",
                                  "enabled": true,
                                  "errorMessage": {
                                      "en": "Required",
                                      "fr": "FR: Required"
                                  },
                                  "name": "require",
                                  "type": "require",
                                  "value": null
                              }
                          ],
                          "dependants": [],
                          "dependencyGroups": [
                              {
                                  "guid": "ca61c4f2-95a4-4348-a07c-024de1a57a9c",
                                  "ruleType": "visibility",
                                  "childValidatorName": null,
                                  "questionDependencies": [
                                      {
                                          "guid": "72b16053-fc7d-41a8-aa45-16bafd36c312",
                                          "dependsOnQuestion": {
                                              "guid": "2a52bb18-ff63-42e6-be03-84afe116deb7"
                                          },
                                          "validationAction": "equal",
                                          "validationValue": "2"
                                      }
                                  ]
                              }
                          ],
                          "childQuestions": [],
                          "result": null
                      }
                  ],
                  "result": null
              },
              {
                  "guid": "6b6cda38-a8a5-4a00-8483-6477389e4111",
                  "name": "6b6cda38-a8a5-4a00-8483-6477389e4111",
                  "sortOrder": 4,
                  "text": {
                      "en": "1.02 Equivalency Certificate Number(s) (if applicable)",
                      "fr": "1.02 Numéro(s) de certificat d'équivalence (si applicable)"
                  },
                  "type": "text",
                  "isRepeatable": true,
                  "isRepeated": false,
                  "isSamplingAllowed": false,
                  "isVisible": true,
                  "validationState": true,
                  "responseOptions": [],
                  "validationRules": [
                      {
                          "guid": "8ab5c7b9-5c74-49e2-ae66-30b496f941d2",
                          "enabled": true,
                          "errorMessage": {
                              "en": "Required",
                              "fr": "FR: Required"
                          },
                          "name": "require",
                          "type": "require",
                          "value": null
                      }
                  ],
                  "dependants": [],
                  "dependencyGroups": [],
                  "childQuestions": [],
                  "result": null
              }
          ],
          "isVisibleByDefault": true,
          "expansionPanels": []
      },
      {
          "domId": "",
          "domSuffix": "",
          "guid": "009df908-4592-4c32-ae31-ed576688dcd2",
          "name": "009df908-4592-4c32-ae31-ed576688dcd2",
          "sortOrder": 2,
          "title": {
              "en": "2.0 CERTIFICATE(S) OF REGISTRATION ",
              "fr": "2.0 CERTIFICAT(S) D'INSCRIPTION"
          },
          "isRepeatable": false,
          "isVisible": true,
          "questions": [
              {
                  "guid": "79a2f09f-18d6-4dc2-9493-688d462f43cb",
                  "name": "79a2f09f-18d6-4dc2-9493-688d462f43cb",
                  "sortOrder": 5,
                  "text": {
                      "en": "2.01 The Certificate of Registration is valid and available upon request.",
                      "fr": "2.01 Le certificat d'inscription est valide et peut être fourni sur demande."
                  },
                  "type": "radio",
                  "isRepeatable": true,
                  "isRepeated": false,
                  "isSamplingAllowed": false,
                  "isVisible": true,
                  "validationState": true,
                  "responseOptions": [
                      {
                          "guid": "29a8436d-db39-4f19-8557-a17bb1d39230",
                          "name": "29a8436d-db39-4f19-8557-a17bb1d39230",
                          "sortOrder": 1,
                          "text": {
                              "en": "Yes",
                              "fr": "Oui"
                          },
                          "value": "true",
                          "internalCommentRequirement": "optional",
                          "externalCommentRequirement": "optional",
                          "pictureRequirement": "optional",
                          "fileRequirement": "optional",
                          "provisions": []
                      },
                      {
                          "guid": "833ce928-ddde-4c5f-9e37-1fc88c489a1e",
                          "name": "833ce928-ddde-4c5f-9e37-1fc88c489a1e",
                          "sortOrder": 2,
                          "text": {
                              "en": "No",
                              "fr": "Non"
                          },
                          "value": "false",
                          "internalCommentRequirement": "optional",
                          "externalCommentRequirement": "required",
                          "pictureRequirement": "optional",
                          "fileRequirement": "optional",
                          "provisions": []
                      },
                      {
                          "guid": "76383f42-cd8d-4ed3-92e2-a791617ef03e",
                          "name": "76383f42-cd8d-4ed3-92e2-a791617ef03e",
                          "sortOrder": 3,
                          "text": {
                              "en": "Not inspected ",
                              "fr": "Non inspecté "
                          },
                          "value": "3",
                          "internalCommentRequirement": "optional",
                          "externalCommentRequirement": "optional",
                          "pictureRequirement": "optional",
                          "fileRequirement": "optional",
                          "provisions": []
                      }
                  ],
                  "validationRules": [
                      {
                          "guid": "b9f62fbe-5272-4185-8672-985d0cecf798",
                          "enabled": true,
                          "errorMessage": {
                              "en": "Required",
                              "fr": "FR: Required"
                          },
                          "name": "require",
                          "type": "require",
                          "value": null
                      }
                  ],
                  "dependants": [
                      {
                          "guid": "fa4551a2-b8a7-4901-a55c-e605141bfaf1"
                      }
                  ],
                  "dependencyGroups": [],
                  "childQuestions": [
                      {
                          "guid": "eba6db28-9707-450b-bab1-3d634642e53b",
                          "name": "eba6db28-9707-450b-bab1-3d634642e53b",
                          "sortOrder": 1,
                          "text": {
                              "en": "2.01a Certificate number ",
                              "fr": "2.01a Numéro du Certificat"
                          },
                          "type": "text",
                          "isRepeatable": true,
                          "isRepeated": false,
                          "isSamplingAllowed": false,
                          "isVisible": true,
                          "validationState": true,
                          "responseOptions": [],
                          "validationRules": [
                              {
                                  "guid": "53b4bc13-5fc8-4ecf-b1b4-1d6bc1b4db4e",
                                  "enabled": true,
                                  "errorMessage": {
                                      "en": "Required",
                                      "fr": "FR: Required"
                                  },
                                  "name": "require",
                                  "type": "require",
                                  "value": null
                              }
                          ],
                          "dependants": [],
                          "dependencyGroups": [],
                          "childQuestions": [],
                          "result": null
                      }
                  ],
                  "result": null
              }
          ],
          "isVisibleByDefault": true,
          "expansionPanels": []
      },
      {
          "domId": "",
          "domSuffix": "",
          "guid": "ee26c679-eebe-431f-86e1-8b38722bb547",
          "name": "ee26c679-eebe-431f-86e1-8b38722bb547",
          "sortOrder": 3,
          "title": {
              "en": "3.0 OTHER DOCUMENTATION",
              "fr": "3.0 DOCUMENTATION ADDITIONNELLE"
          },
          "isRepeatable": false,
          "isVisible": true,
          "questions": [
              {
                  "guid": "892fb479-6bdf-44e0-904a-1d230e221572",
                  "name": "892fb479-6bdf-44e0-904a-1d230e221572",
                  "sortOrder": 8,
                  "text": {
                      "en": "3.01 The ISO 9001 Certificate is valid and available upon request. ",
                      "fr": "3.01 Le certificat ISO 9001 est valide et peut être fourni sur demande."
                  },
                  "type": "radio",
                  "isRepeatable": true,
                  "isRepeated": false,
                  "isSamplingAllowed": false,
                  "isVisible": true,
                  "validationState": true,
                  "responseOptions": [
                      {
                          "guid": "5934eff8-41cd-4f80-a716-178aab35d866",
                          "name": "5934eff8-41cd-4f80-a716-178aab35d866",
                          "sortOrder": 1,
                          "text": {
                              "en": "Yes",
                              "fr": "Oui"
                          },
                          "value": "true",
                          "internalCommentRequirement": "optional",
                          "externalCommentRequirement": "optional",
                          "pictureRequirement": "optional",
                          "fileRequirement": "optional",
                          "provisions": []
                      },
                      {
                          "guid": "c4020df2-7e26-40be-94fc-a612324f9abe",
                          "name": "c4020df2-7e26-40be-94fc-a612324f9abe",
                          "sortOrder": 2,
                          "text": {
                              "en": "No",
                              "fr": "Non"
                          },
                          "value": "false",
                          "internalCommentRequirement": "optional",
                          "externalCommentRequirement": "required",
                          "pictureRequirement": "optional",
                          "fileRequirement": "optional",
                          "provisions": []
                      },
                      {
                          "guid": "7dc4f4c4-a4d5-488e-93a7-114fcc7687ca",
                          "name": "7dc4f4c4-a4d5-488e-93a7-114fcc7687ca",
                          "sortOrder": 3,
                          "text": {
                              "en": "Not inspected ",
                              "fr": "Non inspecté "
                          },
                          "value": "3",
                          "internalCommentRequirement": "optional",
                          "externalCommentRequirement": "optional",
                          "pictureRequirement": "optional",
                          "fileRequirement": "optional",
                          "provisions": []
                      }
                  ],
                  "validationRules": [
                      {
                          "guid": "73a98eb1-073f-425a-aac5-ed8cd31ba5c6",
                          "enabled": true,
                          "errorMessage": {
                              "en": "Required",
                              "fr": "FR: Required"
                          },
                          "name": "require",
                          "type": "require",
                          "value": null
                      }
                  ],
                  "dependants": [
                      {
                          "guid": "dd20066c-82b2-4de8-a423-b4c977e1eb07"
                      }
                  ],
                  "dependencyGroups": [],
                  "childQuestions": [
                      {
                          "guid": "dd20066c-82b2-4de8-a423-b4c977e1eb07",
                          "name": "dd20066c-82b2-4de8-a423-b4c977e1eb07",
                          "sortOrder": 1,
                          "text": {
                              "en": "3.01a ISO 9001 Certificate Number ",
                              "fr": "3.01a Numéro de certificat ISO 9001"
                          },
                          "type": "text",
                          "isRepeatable": true,
                          "isRepeated": false,
                          "isSamplingAllowed": false,
                          "isVisible": true,
                          "validationState": true,
                          "responseOptions": [],
                          "validationRules": [
                              {
                                  "guid": "1ff4095c-dd5e-4408-86ce-f4f8af1ef977",
                                  "enabled": true,
                                  "errorMessage": {
                                      "en": "Required",
                                      "fr": "FR: Required"
                                  },
                                  "name": "require",
                                  "type": "require",
                                  "value": null
                              }
                          ],
                          "dependants": [],
                          "dependencyGroups": [],
                          "childQuestions": [],
                          "result": null
                      }
                  ],
                  "result": null
              },
              {
                  "guid": "0850e6c1-400d-4fc2-ac4f-c343b789a68a",
                  "name": "0850e6c1-400d-4fc2-ac4f-c343b789a68a",
                  "sortOrder": 9,
                  "text": {
                      "en": "3.02 Current version of CGSB-43.146",
                      "fr": "3.02 Version actuelle de la norme CGSB-43.146"
                  },
                  "type": "radio",
                  "isRepeatable": false,
                  "isRepeated": false,
                  "isSamplingAllowed": false,
                  "isVisible": true,
                  "validationState": true,
                  "responseOptions": [
                      {
                          "guid": "255acc82-5f21-4442-94cc-2475bc8bc714",
                          "name": "255acc82-5f21-4442-94cc-2475bc8bc714",
                          "sortOrder": 1,
                          "text": {
                              "en": "Yes",
                              "fr": "Oui"
                          },
                          "value": "true",
                          "internalCommentRequirement": "optional",
                          "externalCommentRequirement": "optional",
                          "pictureRequirement": "optional",
                          "fileRequirement": "optional",
                          "provisions": []
                      },
                      {
                          "guid": "63c9bebc-48b4-479c-9048-9510df043275",
                          "name": "63c9bebc-48b4-479c-9048-9510df043275",
                          "sortOrder": 2,
                          "text": {
                              "en": "No",
                              "fr": "Non"
                          },
                          "value": "false",
                          "internalCommentRequirement": "optional",
                          "externalCommentRequirement": "required",
                          "pictureRequirement": "optional",
                          "fileRequirement": "optional",
                          "provisions": []
                      },
                      {
                          "guid": "468e5a91-3422-46a4-b922-dc51fdfb340d",
                          "name": "468e5a91-3422-46a4-b922-dc51fdfb340d",
                          "sortOrder": 3,
                          "text": {
                              "en": "Not inspected ",
                              "fr": "Non inspecté "
                          },
                          "value": "3",
                          "internalCommentRequirement": "optional",
                          "externalCommentRequirement": "optional",
                          "pictureRequirement": "optional",
                          "fileRequirement": "optional",
                          "provisions": []
                      }
                  ],
                  "validationRules": [
                      {
                          "guid": "875de4a4-5bde-42d0-bbf4-d1511bfd763b",
                          "enabled": true,
                          "errorMessage": {
                              "en": "Required",
                              "fr": "FR: Required"
                          },
                          "name": "require",
                          "type": "require",
                          "value": null
                      }
                  ],
                  "dependants": [],
                  "dependencyGroups": [],
                  "childQuestions": [],
                  "result": null
              },
              {
                  "guid": "97c4bf43-0818-4138-8925-d7828af3f346",
                  "name": "97c4bf43-0818-4138-8925-d7828af3f346",
                  "sortOrder": 10,
                  "text": {
                      "en": "3.03 For Code 21 or 31IBCs – Instrument calibration records available?",
                      "fr": "3.03 Pour les code GRV 21 ou 31 – Dossier d'étalonnage des instruments disponibles ?"
                  },
                  "type": "radio",
                  "isRepeatable": false,
                  "isRepeated": false,
                  "isSamplingAllowed": false,
                  "isVisible": true,
                  "validationState": true,
                  "responseOptions": [
                      {
                          "guid": "ad1916b3-7e2a-407f-b518-d4b7cc4e4747",
                          "name": "ad1916b3-7e2a-407f-b518-d4b7cc4e4747",
                          "sortOrder": 1,
                          "text": {
                              "en": "Yes",
                              "fr": "Oui"
                          },
                          "value": "true",
                          "internalCommentRequirement": "optional",
                          "externalCommentRequirement": "optional",
                          "pictureRequirement": "optional",
                          "fileRequirement": "optional",
                          "provisions": []
                      },
                      {
                          "guid": "1a216e46-bcd2-4c6a-9032-ac8954f84b15",
                          "name": "1a216e46-bcd2-4c6a-9032-ac8954f84b15",
                          "sortOrder": 2,
                          "text": {
                              "en": "No",
                              "fr": "Non"
                          },
                          "value": "false",
                          "internalCommentRequirement": "optional",
                          "externalCommentRequirement": "required",
                          "pictureRequirement": "optional",
                          "fileRequirement": "optional",
                          "provisions": []
                      },
                      {
                          "guid": "80b8ba1e-aa2d-42c2-bf7a-5fe1e4a81b46",
                          "name": "80b8ba1e-aa2d-42c2-bf7a-5fe1e4a81b46",
                          "sortOrder": 3,
                          "text": {
                              "en": "Not inspected ",
                              "fr": "Non inspecté "
                          },
                          "value": "3",
                          "internalCommentRequirement": "optional",
                          "externalCommentRequirement": "optional",
                          "pictureRequirement": "optional",
                          "fileRequirement": "optional",
                          "provisions": []
                      }
                  ],
                  "validationRules": [
                      {
                          "guid": "8a7cdda3-ed8f-4302-b5ef-40b57be0ee59",
                          "enabled": true,
                          "errorMessage": {
                              "en": "Required",
                              "fr": "FR: Required"
                          },
                          "name": "require",
                          "type": "require",
                          "value": null
                      }
                  ],
                  "dependants": [],
                  "dependencyGroups": [],
                  "childQuestions": [],
                  "result": null
              },
              {
                  "guid": "30f89c52-7b09-4676-9221-3716c2c0ea62",
                  "name": "30f89c52-7b09-4676-9221-3716c2c0ea62",
                  "sortOrder": 11,
                  "text": {
                      "en": "3.04 Estimated number of UN IBCs manufactured per month or year ",
                      "fr": "3.04 Nombre approximatif de GRV normalisés UN fabriqués par mois ou année"
                  },
                  "type": "radio",
                  "isRepeatable": false,
                  "isRepeated": false,
                  "isSamplingAllowed": true,
                  "isVisible": true,
                  "validationState": true,
                  "responseOptions": [
                      {
                          "guid": "f8396f4c-9cad-4f99-8148-9b187a6e69bb",
                          "name": "f8396f4c-9cad-4f99-8148-9b187a6e69bb",
                          "sortOrder": 1,
                          "text": {
                              "en": "Per month ",
                              "fr": "Par mois"
                          },
                          "value": "1",
                          "internalCommentRequirement": "optional",
                          "externalCommentRequirement": "optional",
                          "pictureRequirement": "optional",
                          "fileRequirement": "optional",
                          "provisions": []
                      },
                      {
                          "guid": "268cbbae-757a-4452-86bc-f46b71138e51",
                          "name": "268cbbae-757a-4452-86bc-f46b71138e51",
                          "sortOrder": 2,
                          "text": {
                              "en": "Per year ",
                              "fr": "Par année"
                          },
                          "value": "2",
                          "internalCommentRequirement": "optional",
                          "externalCommentRequirement": "required",
                          "pictureRequirement": "optional",
                          "fileRequirement": "optional",
                          "provisions": []
                      },
                      {
                          "guid": "392d2347-b87e-42f3-84ab-a232c929e281",
                          "name": "392d2347-b87e-42f3-84ab-a232c929e281",
                          "sortOrder": 3,
                          "text": {
                              "en": "Not inspected ",
                              "fr": "Non inspecté "
                          },
                          "value": "3",
                          "internalCommentRequirement": "optional",
                          "externalCommentRequirement": "optional",
                          "pictureRequirement": "optional",
                          "fileRequirement": "optional",
                          "provisions": []
                      }
                  ],
                  "validationRules": [
                      {
                          "guid": "35216249-b8ec-4885-993b-d6a34ede7711",
                          "enabled": true,
                          "errorMessage": {
                              "en": "Required",
                              "fr": "FR: Required"
                          },
                          "name": "require",
                          "type": "require",
                          "value": null
                      }
                  ],
                  "dependants": [
                      {
                          "guid": "73857f49-5de0-40c6-8f33-b1cc314cd62f"
                      },
                      {
                          "guid": "3f63f7b9-b0fd-4518-a941-ee8aa96772f1"
                      }
                  ],
                  "dependencyGroups": [],
                  "childQuestions": [
                      {
                          "guid": "73857f49-5de0-40c6-8f33-b1cc314cd62f",
                          "name": "73857f49-5de0-40c6-8f33-b1cc314cd62f",
                          "sortOrder": 1,
                          "text": {
                              "en": "3.04a Per month",
                              "fr": "3.04a Par mois"
                          },
                          "type": "text",
                          "isRepeatable": false,
                          "isRepeated": false,
                          "isSamplingAllowed": false,
                          "isVisible": false,
                          "validationState": true,
                          "responseOptions": [],
                          "validationRules": [
                              {
                                  "guid": "28e7de10-edd4-4bd2-b7b1-5d085393b2f6",
                                  "enabled": true,
                                  "errorMessage": {
                                      "en": "Required",
                                      "fr": "FR: Required"
                                  },
                                  "name": "require",
                                  "type": "require",
                                  "value": null
                              }
                          ],
                          "dependants": [],
                          "dependencyGroups": [
                              {
                                  "guid": "dd2bad4c-7da8-4d1c-b411-1f8bce17e718",
                                  "ruleType": "visibility",
                                  "childValidatorName": null,
                                  "questionDependencies": [
                                      {
                                          "guid": "c89f2880-cf40-4fdd-a90e-346c4cb00f9e",
                                          "dependsOnQuestion": {
                                              "guid": "30f89c52-7b09-4676-9221-3716c2c0ea62"
                                          },
                                          "validationAction": "equal",
                                          "validationValue": "1"
                                      }
                                  ]
                              }
                          ],
                          "childQuestions": [],
                          "result": null
                      },
                      {
                          "guid": "3f63f7b9-b0fd-4518-a941-ee8aa96772f1",
                          "name": "3f63f7b9-b0fd-4518-a941-ee8aa96772f1",
                          "sortOrder": 2,
                          "text": {
                              "en": "3.04b Per year ",
                              "fr": "3.04b Par année"
                          },
                          "type": "text",
                          "isRepeatable": false,
                          "isRepeated": false,
                          "isSamplingAllowed": false,
                          "isVisible": false,
                          "validationState": true,
                          "responseOptions": [],
                          "validationRules": [
                              {
                                  "guid": "fc4f16cf-f14d-47bf-abf5-1d4d71cc2a1b",
                                  "enabled": true,
                                  "errorMessage": {
                                      "en": "Required",
                                      "fr": "FR: Required"
                                  },
                                  "name": "require",
                                  "type": "require",
                                  "value": null
                              }
                          ],
                          "dependants": [],
                          "dependencyGroups": [
                              {
                                  "guid": "a14d2e18-c875-49c1-9ce7-1ffa0139a94d",
                                  "ruleType": "visibility",
                                  "childValidatorName": null,
                                  "questionDependencies": [
                                      {
                                          "guid": "dd1d3825-a6ec-493c-902b-6d24c0854449",
                                          "dependsOnQuestion": {
                                              "guid": "30f89c52-7b09-4676-9221-3716c2c0ea62"
                                          },
                                          "validationAction": "equal",
                                          "validationValue": "2"
                                      }
                                  ]
                              }
                          ],
                          "childQuestions": [],
                          "result": null
                      }
                  ],
                  "result": null
              }
          ],
          "isVisibleByDefault": true,
          "expansionPanels": []
      },
      {
          "domId": "",
          "domSuffix": "",
          "guid": "59423808-51c1-4800-a69c-907f50184c50",
          "name": "59423808-51c1-4800-a69c-907f50184c50",
          "sortOrder": 4,
          "title": {
              "en": "4.0 COMPLIANCE MARKING",
              "fr": "4.0 INDICATION DE CONFORMITÉ"
          },
          "isRepeatable": false,
          "isVisible": true,
          "questions": [
              {
                  "guid": "7d290d74-fb77-4f5a-b966-6225156eea35",
                  "name": "7d290d74-fb77-4f5a-b966-6225156eea35",
                  "sortOrder": 13,
                  "text": {
                      "en": "4.01 Compliance markings comply with section 5 of CGSB-43.146",
                      "fr": "4.01 Les indications de conformités rencontrent les exigences de la section 5 de la norme CGSB-43.146"
                  },
                  "type": "radio",
                  "isRepeatable": false,
                  "isRepeated": false,
                  "isSamplingAllowed": false,
                  "isVisible": true,
                  "validationState": true,
                  "responseOptions": [
                      {
                          "guid": "a6df0648-a3e0-4f43-8824-132d9ae862d1",
                          "name": "a6df0648-a3e0-4f43-8824-132d9ae862d1",
                          "sortOrder": 1,
                          "text": {
                              "en": "Yes",
                              "fr": "Oui"
                          },
                          "value": "true",
                          "internalCommentRequirement": "optional",
                          "externalCommentRequirement": "optional",
                          "pictureRequirement": "optional",
                          "fileRequirement": "optional",
                          "provisions": []
                      },
                      {
                          "guid": "83f3c528-e9ce-4f8d-b883-59e6ef22da23",
                          "name": "83f3c528-e9ce-4f8d-b883-59e6ef22da23",
                          "sortOrder": 2,
                          "text": {
                              "en": "No",
                              "fr": "Non"
                          },
                          "value": "false",
                          "internalCommentRequirement": "optional",
                          "externalCommentRequirement": "required",
                          "pictureRequirement": "optional",
                          "fileRequirement": "optional",
                          "provisions": []
                      },
                      {
                          "guid": "7de100ea-a488-43f8-8a44-cfa6396af7ba",
                          "name": "7de100ea-a488-43f8-8a44-cfa6396af7ba",
                          "sortOrder": 3,
                          "text": {
                              "en": "Not inspected ",
                              "fr": "Non inspecté "
                          },
                          "value": "3",
                          "internalCommentRequirement": "optional",
                          "externalCommentRequirement": "optional",
                          "pictureRequirement": "optional",
                          "fileRequirement": "optional",
                          "provisions": []
                      }
                  ],
                  "validationRules": [
                      {
                          "guid": "e8b1df45-1871-4849-99f6-0f705cc22927",
                          "enabled": true,
                          "errorMessage": {
                              "en": "Required",
                              "fr": "FR: Required"
                          },
                          "name": "require",
                          "type": "require",
                          "value": null
                      }
                  ],
                  "dependants": [],
                  "dependencyGroups": [],
                  "childQuestions": [],
                  "result": null
              },
              {
                  "guid": "1025317b-6337-4f41-b9ad-613f59c777ad",
                  "name": "1025317b-6337-4f41-b9ad-613f59c777ad",
                  "sortOrder": 14,
                  "text": {
                      "en": "4.02 Copy of compliance markings attached to this report (handwritten or photo)",
                      "fr": "4.02 Copie des indications de conformité jointes au présent document (copie manuscrite ou photo)"
                  },
                  "type": "radio",
                  "isRepeatable": true,
                  "isRepeated": false,
                  "isSamplingAllowed": false,
                  "isVisible": false,
                  "validationState": true,
                  "responseOptions": [
                      {
                          "guid": "5fe0e0be-56d3-44dc-92a5-2b9d0fff13f5",
                          "name": "5fe0e0be-56d3-44dc-92a5-2b9d0fff13f5",
                          "sortOrder": 1,
                          "text": {
                              "en": "Yes",
                              "fr": "Oui"
                          },
                          "value": "true",
                          "internalCommentRequirement": "optional",
                          "externalCommentRequirement": "optional",
                          "pictureRequirement": "optional",
                          "fileRequirement": "optional",
                          "provisions": []
                      },
                      {
                          "guid": "6abcd965-5a55-40d7-9967-b8243e6232e8",
                          "name": "6abcd965-5a55-40d7-9967-b8243e6232e8",
                          "sortOrder": 2,
                          "text": {
                              "en": "No",
                              "fr": "Non"
                          },
                          "value": "true",
                          "internalCommentRequirement": "optional",
                          "externalCommentRequirement": "optional",
                          "pictureRequirement": "optional",
                          "fileRequirement": "optional",
                          "provisions": []
                      },
                      {
                          "guid": "69f72594-a039-4e21-9574-ccb3140be247",
                          "name": "69f72594-a039-4e21-9574-ccb3140be247",
                          "sortOrder": 3,
                          "text": {
                              "en": "Not inspected ",
                              "fr": "Non inspecté "
                          },
                          "value": "3",
                          "internalCommentRequirement": "optional",
                          "externalCommentRequirement": "optional",
                          "pictureRequirement": "optional",
                          "fileRequirement": "optional",
                          "provisions": []
                      }
                  ],
                  "validationRules": [
                      {
                          "guid": "2da00f9c-61da-428e-ab49-262e751e520e",
                          "enabled": true,
                          "errorMessage": {
                              "en": "Required",
                              "fr": "FR: Required"
                          },
                          "name": "require",
                          "type": "require",
                          "value": null
                      }
                  ],
                  "dependants": [],
                  "dependencyGroups": [],
                  "childQuestions": [],
                  "result": null
              }
          ],
          "isVisibleByDefault": true,
          "expansionPanels": []
      },
      {
          "domId": "",
          "domSuffix": "",
          "guid": "58439a03-396a-4375-b2f1-7d9a6936e079",
          "name": "58439a03-396a-4375-b2f1-7d9a6936e079",
          "sortOrder": 5,
          "title": {
              "en": "5.0 ADDITIONAL NON-COMPLIANCES",
              "fr": "5.0 AUTRES NON-CONFORMITÉS"
          },
          "isRepeatable": true,
          "isVisible": true,
          "questions": [
              {
                  "guid": "bfb8483d-6f20-49e1-9b32-cbbf072817f8",
                  "name": "bfb8483d-6f20-49e1-9b32-cbbf072817f8",
                  "sortOrder": 19,
                  "text": {
                      "en": "5.01 Additional non-compliances ",
                      "fr": "5.01 Autres non-conformités"
                  },
                  "type": "text",
                  "isRepeatable": true,
                  "isRepeated": false,
                  "isSamplingAllowed": true,
                  "isVisible": true,
                  "validationState": true,
                  "responseOptions": [],
                  "validationRules": [
                      {
                          "guid": "6b477daa-3b5f-42bb-b7ff-80807c6fe448",
                          "enabled": true,
                          "errorMessage": {
                              "en": "Required",
                              "fr": "FR: Required"
                          },
                          "name": "require",
                          "type": "require",
                          "value": null
                      }
                  ],
                  "dependants": [],
                  "dependencyGroups": [],
                  "childQuestions": [],
                  "result": null
              }
          ],
          "isVisibleByDefault": true,
          "expansionPanels": []
      }
  ],
  "searchableProvisions": []
}